[
  {
    "id": 99,
    "data": {
      "image": "/data/local-files/?d=media/abolfazl/BiggerData/test_tiles_55/jpgs/Jefferson_127.jpg"
    },
    "meta": {},
    "created_at": "2021-06-01T02:05:50.031832Z",
    "updated_at": "2021-06-01T02:05:50.031840Z",
    "is_labeled": true,
    "overlap": 1,
    "project": 2,
    "file_upload": 126,
    "annotations": [
      {
        "id": 214,
        "created_username": " lu.liang@unt.edu, 4",
        "created_ago": "1\u00a0day, 17\u00a0hours",
        "completed_by": 4,
        "result": [
          {
            "original_width": 5000,
            "original_height": 5000,
            "image_rotation": 0,
            "value": {
              "points": [
                [
                  45.924050632911396,
                  0
                ],
                [
                  54.050632911392405,
                  0.02531645569620253
                ],
                [
                  53.18987341772151,
                  1.620253164556962
                ],
                [
                  51.848101265822784,
                  4.10126582278481
                ],
                [
                  50.784810126582286,
                  6.278481012658227
                ],
                [
                  49.746835443037966,
                  8.10126582278481
                ],
                [
                  46.32911392405063,
                  8.481012658227847
                ],
                [
                  45.949367088607595,
                  8.430379746835444
                ]
              ],
              "polygonlabels": [
                "z"
              ]
            },
            "id": "cydsfFtZqI",
            "from_name": "label",
            "to_name": "image",
            "type": "polygonlabels"
          },
          {
            "original_width": 5000,
            "original_height": 5000,
            "image_rotation": 0,
            "value": {
              "points": [
                [
                  87.67088607594938,
                  94.43037974683544
                ],
                [
                  90.2278481012658,
                  94.30379746835443
                ],
                [
                  95.0632911392405,
                  99.97468354430379
                ],
                [
                  87.8481012658228,
                  99.94936708860759
                ],
                [
                  87.56962025316457,
                  94.65822784810125
                ]
              ],
              "polygonlabels": [
                "z"
              ]
            },
            "id": "CHSPybfLQT",
            "from_name": "label",
            "to_name": "image",
            "type": "polygonlabels"
          },
          {
            "original_width": 5000,
            "original_height": 5000,
            "image_rotation": 0,
            "value": {
              "points": [
                [
                  69.41772151898734,
                  97.67088607594937
                ],
                [
                  81.67088607594937,
                  97.62025316455696
                ],
                [
                  82.02531645569618,
                  97.74683544303795
                ],
                [
                  81.94936708860757,
                  99.94936708860759
                ],
                [
                  69.46835443037975,
                  100
                ],
                [
                  69.26582278481013,
                  98.35443037974683
                ],
                [
                  69.21518987341773,
                  97.82278481012658
                ]
              ],
              "polygonlabels": [
                "c"
              ]
            },
            "id": "EO8SSz2sqL",
            "from_name": "label",
            "to_name": "image",
            "type": "polygonlabels"
          },
          {
            "original_width": 5000,
            "original_height": 5000,
            "image_rotation": 0,
            "value": {
              "points": [
                [
                  58.531645569620245,
                  93.72151898734177
                ],
                [
                  64.81012658227849,
                  93.82278481012658
                ],
                [
                  65.87341772151898,
                  94.53164556962027
                ],
                [
                  65.77215189873418,
                  99.97468354430379
                ],
                [
                  58.27848101265822,
                  99.94936708860759
                ],
                [
                  58.30379746835443,
                  93.84810126582279
                ]
              ],
              "polygonlabels": [
                "z"
              ]
            },
            "id": "J613QI5kJD",
            "from_name": "label",
            "to_name": "image",
            "type": "polygonlabels"
          },
          {
            "original_width": 5000,
            "original_height": 5000,
            "image_rotation": 0,
            "value": {
              "points": [
                [
                  66.83544303797468,
                  73.26582278481013
                ],
                [
                  77.89873417721519,
                  73.26582278481013
                ],
                [
                  78.75949367088607,
                  74
                ],
                [
                  79.0886075949367,
                  74.68354430379746
                ],
                [
                  80.17721518987342,
                  77.74683544303797
                ],
                [
                  80.96202531645568,
                  81.64556962025317
                ],
                [
                  80.9873417721519,
                  82.15189873417721
                ],
                [
                  80.73417721518987,
                  82.55696202531644
                ],
                [
                  80.53164556962025,
                  82.73417721518987
                ],
                [
                  66.81012658227849,
                  82.83544303797467
                ],
                [
                  66.60759493670886,
                  82.70886075949367
                ],
                [
                  66.65822784810126,
                  73.49367088607593
                ]
              ],
              "polygonlabels": [
                "c"
              ]
            },
            "id": "33G6QkAW1p",
            "from_name": "label",
            "to_name": "image",
            "type": "polygonlabels"
          },
          {
            "original_width": 5000,
            "original_height": 5000,
            "image_rotation": 0,
            "value": {
              "points": [
                [
                  66.63291139240506,
                  66.9620253164557
                ],
                [
                  66.81012658227849,
                  72.9367088607595
                ],
                [
                  66.91139240506328,
                  73.1392405063291
                ],
                [
                  67.46835443037975,
                  73.21518987341773
                ],
                [
                  68.27848101265822,
                  73.03797468354429
                ],
                [
                  68.65822784810126,
                  72.88607594936708
                ],
                [
                  76.9873417721519,
                  73.1139240506329
                ],
                [
                  77.64556962025317,
                  72.9873417721519
                ],
                [
                  75.51898734177215,
                  71.44303797468355
                ],
                [
                  75.16455696202532,
                  70.91139240506328
                ],
                [
                  74.91139240506328,
                  70.43037974683544
                ],
                [
                  74.91139240506328,
                  69.69620253164557
                ],
                [
                  74.73417721518987,
                  68.83544303797468
                ],
                [
                  74.50632911392405,
                  68.58227848101265
                ],
                [
                  74.0253164556962,
                  68.55696202531645
                ],
                [
                  73.72151898734177,
                  68.35443037974683
                ],
                [
                  73.56962025316456,
                  68.0759493670886
                ],
                [
                  73.39240506329114,
                  68
                ],
                [
                  72.78481012658227,
                  67.77215189873418
                ],
                [
                  72.48101265822784,
                  67.49367088607593
                ],
                [
                  72.43037974683544,
                  67.1139240506329
                ],
                [
                  72.25316455696202,
                  66.91139240506328
                ],
                [
                  66.88607594936708,
                  66.88607594936708
                ]
              ],
              "polygonlabels": [
                "z"
              ]
            },
            "id": "jcEZCAdA55",
            "from_name": "label",
            "to_name": "image",
            "type": "polygonlabels"
          },
          {
            "original_width": 5000,
            "original_height": 5000,
            "image_rotation": 0,
            "value": {
              "points": [
                [
                  31.037974683544302,
                  67.54430379746836
                ],
                [
                  38.48101265822785,
                  67.64556962025317
                ],
                [
                  38.43037974683544,
                  75.46835443037975
                ],
                [
                  31.367088607594937,
                  75.49367088607593
                ],
                [
                  30.936708860759484,
                  75.18987341772151
                ],
                [
                  30.835443037974688,
                  67.69620253164557
                ]
              ],
              "polygonlabels": [
                "u"
              ]
            },
            "id": "w0ePH2x1F4",
            "from_name": "label",
            "to_name": "image",
            "type": "polygonlabels"
          },
          {
            "original_width": 5000,
            "original_height": 5000,
            "image_rotation": 0,
            "value": {
              "points": [
                [
                  31.215189873417724,
                  75.54430379746834
                ],
                [
                  38.734177215189874,
                  75.59493670886076
                ],
                [
                  38.93670886075949,
                  75.74683544303797
                ],
                [
                  39.0126582278481,
                  83.26582278481011
                ],
                [
                  38.78481012658228,
                  83.36708860759492
                ],
                [
                  36.9873417721519,
                  83.51898734177217
                ],
                [
                  32.25316455696203,
                  83.41772151898736
                ],
                [
                  31.164556962025312,
                  83.34177215189875
                ],
                [
                  31.037974683544302,
                  75.74683544303797
                ]
              ],
              "polygonlabels": [
                "u"
              ]
            },
            "id": "k4ATnQiKMP",
            "from_name": "label",
            "to_name": "image",
            "type": "polygonlabels"
          },
          {
            "original_width": 5000,
            "original_height": 5000,
            "image_rotation": 0,
            "value": {
              "points": [
                [
                  39.392405063291136,
                  75.62025316455696
                ],
                [
                  46.45569620253164,
                  75.72151898734177
                ],
                [
                  46.58227848101265,
                  75.87341772151898
                ],
                [
                  46.55696202531645,
                  83.03797468354432
                ],
                [
                  46.379746835443036,
                  83.31645569620252
                ],
                [
                  45.949367088607595,
                  83.41772151898736
                ],
                [
                  39.21518987341772,
                  83.44303797468353
                ],
                [
                  39.063291139240505,
                  83.29113924050631
                ],
                [
                  38.93670886075949,
                  75.92405063291139
                ],
                [
                  39.11392405063291,
                  75.64556962025317
                ]
              ],
              "polygonlabels": [
                "u"
              ]
            },
            "id": "1VVvgefpSo",
            "from_name": "label",
            "to_name": "image",
            "type": "polygonlabels"
          },
          {
            "original_width": 5000,
            "original_height": 5000,
            "image_rotation": 0,
            "value": {
              "points": [
                [
                  4.2025316455696204,
                  64.78481012658227
                ],
                [
                  12.93670886075949,
                  59.417721518987335
                ],
                [
                  14.37974683544304,
                  59.39240506329114
                ],
                [
                  14.30379746835443,
                  67.34177215189874
                ],
                [
                  13.974683544303797,
                  67.36708860759492
                ],
                [
                  8.886075949367088,
                  67.29113924050633
                ],
                [
                  8.430379746835444,
                  67.56962025316456
                ],
                [
                  8.151898734177216,
                  67.74683544303797
                ],
                [
                  7.873417721518987,
                  67.59493670886076
                ],
                [
                  6.9367088607594924,
                  66.73417721518987
                ],
                [
                  4.911392405063291,
                  65.79746835443038
                ],
                [
                  4.379746835443037,
                  65.49367088607593
                ],
                [
                  4.177215189873418,
                  65.18987341772151
                ]
              ],
              "polygonlabels": [
                "z"
              ]
            },
            "id": "5Bp4hERxr5",
            "from_name": "label",
            "to_name": "image",
            "type": "polygonlabels"
          },
          {
            "original_width": 5000,
            "original_height": 5000,
            "image_rotation": 0,
            "value": {
              "points": [
                [
                  8.91139240506329,
                  67.89873417721519
                ],
                [
                  12.708860759493671,
                  67.82278481012658
                ],
                [
                  13.037974683544304,
                  67.9746835443038
                ],
                [
                  13.08860759493671,
                  83.31645569620252
                ],
                [
                  8.379746835443036,
                  83.29113924050631
                ],
                [
                  6.860759493670886,
                  75.92405063291139
                ],
                [
                  6.886075949367087,
                  75.21518987341773
                ],
                [
                  7.696202531645569,
                  72.73417721518987
                ],
                [
                  8.556962025316455,
                  68.48101265822784
                ],
                [
                  8.759493670886075,
                  68.15189873417721
                ]
              ],
              "polygonlabels": [
                "z"
              ]
            },
            "id": "zo_3rujZ3t",
            "from_name": "label",
            "to_name": "image",
            "type": "polygonlabels"
          },
          {
            "original_width": 5000,
            "original_height": 5000,
            "image_rotation": 0,
            "value": {
              "points": [
                [
                  13.291139240506329,
                  67.94936708860759
                ],
                [
                  18.177215189873415,
                  67.9746835443038
                ],
                [
                  18.481012658227847,
                  67.9746835443038
                ],
                [
                  18.68354430379747,
                  68.12658227848101
                ],
                [
                  18.759493670886073,
                  83.31645569620252
                ],
                [
                  18.582278481012654,
                  83.39240506329114
                ],
                [
                  13.544303797468352,
                  83.46835443037973
                ],
                [
                  13.189873417721522,
                  83.26582278481011
                ],
                [
                  13.11392405063291,
                  68.17721518987342
                ]
              ],
              "polygonlabels": [
                "z"
              ]
            },
            "id": "m70CIksVXw",
            "from_name": "label",
            "to_name": "image",
            "type": "polygonlabels"
          },
          {
            "original_width": 5000,
            "original_height": 5000,
            "image_rotation": 0,
            "value": {
              "points": [
                [
                  9.848101265822784,
                  84.0759493670886
                ],
                [
                  10.22784810126582,
                  84.0253164556962
                ],
                [
                  10.556962025316453,
                  84.126582278481
                ],
                [
                  11.063291139240503,
                  84.126582278481
                ],
                [
                  11.417721518987344,
                  84.0253164556962
                ],
                [
                  11.974683544303799,
                  83.89873417721519
                ],
                [
                  17.367088607594937,
                  83.87341772151898
                ],
                [
                  17.51898734177215,
                  91.06329113924052
                ],
                [
                  17.265822784810126,
                  91.39240506329114
                ],
                [
                  7.18987341772152,
                  91.44303797468356
                ],
                [
                  6.91139240506329,
                  91.1645569620253
                ],
                [
                  6.6075949367088604,
                  90.30379746835442
                ],
                [
                  6.531645569620253,
                  89.59493670886076
                ],
                [
                  6.658227848101266,
                  88.93670886075948
                ],
                [
                  7.974683544303797,
                  86.48101265822784
                ],
                [
                  8.177215189873417,
                  85.74683544303794
                ],
                [
                  8.430379746835444,
                  85.34177215189874
                ],
                [
                  9.443037974683543,
                  84.81012658227849
                ],
                [
                  9.620253164556962,
                  84.27848101265823
                ]
              ],
              "polygonlabels": [
                "z"
              ]
            },
            "id": "PpfUkAqlvF",
            "from_name": "label",
            "to_name": "image",
            "type": "polygonlabels"
          },
          {
            "original_width": 5000,
            "original_height": 5000,
            "image_rotation": 0,
            "value": {
              "points": [
                [
                  9.645569620253164,
                  91.62025316455696
                ],
                [
                  17.367088607594937,
                  91.62025316455696
                ],
                [
                  17.645569620253163,
                  91.69620253164557
                ],
                [
                  17.772151898734176,
                  99.92405063291139
                ],
                [
                  15.848101265822786,
                  99.92405063291139
                ],
                [
                  15.240506329113924,
                  97.9493670886076
                ],
                [
                  14.784810126582279,
                  97.1898734177215
                ],
                [
                  14.683544303797468,
                  96.02531645569618
                ],
                [
                  14.50632911392405,
                  94.48101265822783
                ],
                [
                  14.481012658227849,
                  94.07594936708861
                ],
                [
                  13.392405063291138,
                  93.82278481012658
                ],
                [
                  13.063291139240507,
                  93.41772151898735
                ],
                [
                  12.632911392405063,
                  93.2151898734177
                ],
                [
                  11.974683544303799,
                  93.2151898734177
                ],
                [
                  10.278481012658228,
                  93.2151898734177
                ],
                [
                  9.974683544303797,
                  93.18987341772151
                ],
                [
                  9.620253164556962,
                  92.88607594936708
                ],
                [
                  9.493670886075948,
                  92.45569620253163
                ]
              ],
              "polygonlabels": [
                "z"
              ]
            },
            "id": "UMMdYKAZtw",
            "from_name": "label",
            "to_name": "image",
            "type": "polygonlabels"
          },
          {
            "original_width": 5000,
            "original_height": 5000,
            "image_rotation": 0,
            "value": {
              "points": [
                [
                  0,
                  73.29113924050633
                ],
                [
                  0,
                  83.51898734177217
                ],
                [
                  6.7594936708860756,
                  83.51898734177217
                ],
                [
                  7.088607594936708,
                  83.49367088607593
                ],
                [
                  7.139240506329114,
                  83.13924050632913
                ],
                [
                  5.772151898734177,
                  76.25316455696202
                ],
                [
                  5.8734177215189876,
                  75.18987341772151
                ],
                [
                  6.253164556962026,
                  73.49367088607593
                ],
                [
                  6.278481012658227,
                  73.29113924050633
                ],
                [
                  0.37974683544303794,
                  73.31645569620252
                ],
                [
                  0.27848101265822783,
                  73.31645569620252
                ]
              ],
              "polygonlabels": [
                "z"
              ]
            },
            "id": "xwdjDQjAcz",
            "from_name": "label",
            "to_name": "image",
            "type": "polygonlabels"
          },
          {
            "original_width": 5000,
            "original_height": 5000,
            "image_rotation": 0,
            "value": {
              "points": [
                [
                  0,
                  62.075949367088604
                ],
                [
                  0,
                  73.1392405063291
                ],
                [
                  5.999999999999999,
                  73.0886075949367
                ],
                [
                  6.30379746835443,
                  73.03797468354429
                ],
                [
                  6.531645569620253,
                  72.45569620253164
                ],
                [
                  7.113924050632911,
                  69.41772151898734
                ],
                [
                  7.139240506329114,
                  68.86075949367088
                ],
                [
                  6.7594936708860756,
                  68.12658227848101
                ],
                [
                  3.113924050632911,
                  66.25316455696202
                ],
                [
                  2.683544303797468,
                  65.79746835443038
                ]
              ],
              "polygonlabels": [
                "z"
              ]
            },
            "id": "GM52ee3TEe",
            "from_name": "label",
            "to_name": "image",
            "type": "polygonlabels"
          },
          {
            "original_width": 5000,
            "original_height": 5000,
            "image_rotation": 0,
            "value": {
              "points": [
                [
                  0,
                  48.32911392405064
                ],
                [
                  0,
                  60.88607594936709
                ],
                [
                  0.4050632911392405,
                  60.632911392405056
                ],
                [
                  0.7088607594936709,
                  60.10126582278481
                ],
                [
                  5.89873417721519,
                  48.455696202531634
                ],
                [
                  5.949367088607595,
                  48.101265822784804
                ]
              ],
              "polygonlabels": [
                "z"
              ]
            },
            "id": "V4nnVEz1f8",
            "from_name": "label",
            "to_name": "image",
            "type": "polygonlabels"
          },
          {
            "original_width": 5000,
            "original_height": 5000,
            "image_rotation": 0,
            "value": {
              "points": [
                [
                  0,
                  25.518987341772153
                ],
                [
                  9.544303797468354,
                  25.417721518987342
                ],
                [
                  9.79746835443038,
                  25.44303797468354
                ],
                [
                  9.544303797468354,
                  25.89873417721519
                ],
                [
                  8.632911392405063,
                  26.60759493670886
                ],
                [
                  8.354430379746836,
                  27.39240506329114
                ],
                [
                  8.430379746835444,
                  31.82278481012658
                ],
                [
                  8.050632911392405,
                  31.79746835443038
                ],
                [
                  0.02531645569620253,
                  31.77215189873418
                ]
              ],
              "polygonlabels": [
                "z"
              ]
            },
            "id": "KroPXl1rb8",
            "from_name": "label",
            "to_name": "image",
            "type": "polygonlabels"
          },
          {
            "original_width": 5000,
            "original_height": 5000,
            "image_rotation": 0,
            "value": {
              "points": [
                [
                  0,
                  32.025316455696206
                ],
                [
                  0.02531645569620253,
                  39.291139240506325
                ],
                [
                  7.51898734177215,
                  39.21518987341772
                ],
                [
                  8.025316455696201,
                  39.21518987341772
                ],
                [
                  8.20253164556962,
                  39.13924050632911
                ],
                [
                  8.430379746835444,
                  36.075949367088604
                ],
                [
                  8.455696202531646,
                  35.18987341772152
                ],
                [
                  8.506329113924052,
                  33.848101265822784
                ],
                [
                  8.405063291139241,
                  32.32911392405063
                ],
                [
                  8.354430379746836,
                  32
                ],
                [
                  0.3037974683544304,
                  31.974683544303797
                ],
                [
                  0.27848101265822783,
                  32.025316455696206
                ]
              ],
              "polygonlabels": [
                "z"
              ]
            },
            "id": "RSFX20g_34",
            "from_name": "label",
            "to_name": "image",
            "type": "polygonlabels"
          },
          {
            "original_width": 5000,
            "original_height": 5000,
            "image_rotation": 0,
            "value": {
              "points": [
                [
                  0.02531645569620253,
                  39.56962025316455
                ],
                [
                  0.05063291139240506,
                  47.56962025316456
                ],
                [
                  3.8987341772151893,
                  47.518987341772146
                ],
                [
                  4.911392405063291,
                  47.46835443037974
                ],
                [
                  5.670886075949367,
                  47.341772151898724
                ],
                [
                  6.126582278481013,
                  47.341772151898724
                ],
                [
                  6.430379746835442,
                  46.9873417721519
                ],
                [
                  8.329113924050633,
                  42.835443037974684
                ],
                [
                  8.30379746835443,
                  42.27848101265822
                ],
                [
                  8.30379746835443,
                  39.64556962025316
                ],
                [
                  8.177215189873417,
                  39.44303797468354
                ]
              ],
              "polygonlabels": [
                "z"
              ]
            },
            "id": "--GqJ-xhua",
            "from_name": "label",
            "to_name": "image",
            "type": "polygonlabels"
          },
          {
            "original_width": 5000,
            "original_height": 5000,
            "image_rotation": 0,
            "value": {
              "points": [
                [
                  2.5217391304347823,
                  89.2463768115942
                ],
                [
                  6.231884057971014,
                  85.65217391304348
                ],
                [
                  6.434782608695651,
                  85.65217391304348
                ],
                [
                  6.376811594202898,
                  86.81159420289853
                ],
                [
                  5.362318840579711,
                  88.49275362318839
                ],
                [
                  5.101449275362318,
                  89.73913043478261
                ],
                [
                  5.188405797101449,
                  90.63768115942027
                ],
                [
                  5.420289855072464,
                  91.44927536231883
                ],
                [
                  5.6231884057971016,
                  91.94202898550724
                ],
                [
                  5.652173913043478,
                  92.63768115942028
                ],
                [
                  5.449275362318841,
                  93.2173913043478
                ],
                [
                  4.202898550724638,
                  94.95652173913042
                ],
                [
                  3.36231884057971,
                  95.24637681159422
                ],
                [
                  3.1594202898550714,
                  95.44927536231882
                ],
                [
                  2.3768115942028984,
                  96.52173913043478
                ],
                [
                  2.231884057971014,
                  96.46376811594202
                ],
                [
                  2.3478260869565215,
                  89.53623188405795
                ]
              ],
              "polygonlabels": [
                "z"
              ]
            },
            "id": "_sjM3e5a5Y",
            "from_name": "label",
            "to_name": "image",
            "type": "polygonlabels"
          },
          {
            "original_width": 5000,
            "original_height": 5000,
            "image_rotation": 0,
            "value": {
              "points": [
                [
                  1.072463768115942,
                  83.94202898550724
                ],
                [
                  3.1594202898550714,
                  84.05797101449274
                ],
                [
                  5.7971014492753605,
                  84.57971014492752
                ],
                [
                  6.057971014492753,
                  84.66666666666666
                ],
                [
                  6.144927536231885,
                  84.95652173913044
                ],
                [
                  5.942028985507246,
                  85.30434782608694
                ],
                [
                  5.507246376811594,
                  85.79710144927537
                ],
                [
                  1.8840579710144925,
                  89.07246376811594
                ],
                [
                  1.4492753623188401,
                  97.44927536231883
                ],
                [
                  1.2753623188405796,
                  97.53623188405795
                ],
                [
                  0.9855072463768116,
                  84.14492753623189
                ]
              ],
              "polygonlabels": [
                "z"
              ]
            },
            "id": "YLXKqHBqv6",
            "from_name": "label",
            "to_name": "image",
            "type": "polygonlabels"
          },
          {
            "original_width": 5000,
            "original_height": 5000,
            "image_rotation": 0,
            "value": {
              "points": [
                [
                  0,
                  83.76811594202897
                ],
                [
                  0,
                  91.04347826086955
                ],
                [
                  1.0144927536231882,
                  91.13043478260866
                ],
                [
                  0.9855072463768116,
                  83.8550724637681
                ],
                [
                  0.2318840579710144,
                  83.76811594202897
                ]
              ],
              "polygonlabels": [
                "z"
              ]
            },
            "id": "n8RvwDb3c6",
            "from_name": "label",
            "to_name": "image",
            "type": "polygonlabels"
          },
          {
            "original_width": 5000,
            "original_height": 5000,
            "image_rotation": 0,
            "value": {
              "points": [
                [
                  0,
                  91.2463768115942
                ],
                [
                  0.9565217391304347,
                  91.30434782608695
                ],
                [
                  1.072463768115942,
                  91.39130434782608
                ],
                [
                  1.217391304347826,
                  99.94202898550724
                ],
                [
                  0,
                  99.94202898550724
                ]
              ],
              "polygonlabels": [
                "z"
              ]
            },
            "id": "5hHVv0tg7k",
            "from_name": "label",
            "to_name": "image",
            "type": "polygonlabels"
          },
          {
            "original_width": 5000,
            "original_height": 5000,
            "image_rotation": 0,
            "value": {
              "points": [
                [
                  47,
                  73.41666666666667
                ],
                [
                  57.833333333333336,
                  73.16666666666667
                ],
                [
                  58.166666666666664,
                  73.875
                ],
                [
                  58.375,
                  83.04166666666666
                ],
                [
                  47.083333333333336,
                  83.125
                ]
              ],
              "polygonlabels": [
                "c"
              ]
            },
            "id": "pVWZevdTQm",
            "from_name": "label",
            "to_name": "image",
            "type": "polygonlabels"
          },
          {
            "original_width": 5000,
            "original_height": 5000,
            "image_rotation": 0,
            "value": {
              "points": [
                [
                  47.266702685592335,
                  83.6692196681958
                ],
                [
                  46.68223265266461,
                  84.35683147164019
                ],
                [
                  46.75099383300905,
                  99.07172406535007
                ],
                [
                  57.78716327829146,
                  99.00296288500563
                ],
                [
                  57.959066229152555,
                  83.49731671733471
                ]
              ],
              "polygonlabels": [
                "s"
              ]
            },
            "id": "yMAOdxv8aN",
            "from_name": "label",
            "to_name": "image",
            "type": "polygonlabels"
          },
          {
            "original_width": 5000,
            "original_height": 5000,
            "image_rotation": 0,
            "value": {
              "points": [
                [
                  58.50915567190807,
                  73.63008733790774
                ],
                [
                  58.64667803259694,
                  83.25665258612916
                ],
                [
                  58.19973036035808,
                  83.77236143871245
                ],
                [
                  58.26849154070253,
                  93.36454609676166
                ],
                [
                  64.86956485376864,
                  93.50206845745053
                ],
                [
                  65.90098255893523,
                  93.91463553951716
                ],
                [
                  65.66031842772968,
                  83.25665258612916
                ],
                [
                  65.93536314910743,
                  82.98160786475141
                ],
                [
                  66.45107200169073,
                  82.7753243237181
                ],
                [
                  66.45107200169073,
                  74.35207973152434
                ],
                [
                  66.31354964100184,
                  73.25190084601334
                ],
                [
                  59.09362570483579,
                  73.18313966566889
                ],
                [
                  58.749819803113596,
                  73.25190084601334
                ]
              ],
              "polygonlabels": [
                "s"
              ]
            },
            "id": "9gV4Twt1fK",
            "from_name": "label",
            "to_name": "image",
            "type": "polygonlabels"
          }
        ],
        "was_cancelled": false,
        "ground_truth": false,
        "created_at": "2021-06-05T21:24:33.132714Z",
        "updated_at": "2021-06-05T21:24:33.132734Z",
        "lead_time": 95.326,
        "task": 99
      }
    ]
  }
]